[{"model": "game.charge", "pk": 1, "fields": {"zero_apartments": 50, "one_apartments": 250, "two_apartments": 750, "three_apartments": 1500, "four_apartments": 1750, "five_apartments": 2000}}, {"model": "game.card", "pk": 1, "fields": {"name": "B5", "cost": 500, "apartment_cost": 500, "hotel_cost": 2500, "deposit_value": 250, "charge": 1, "group_number": 0, "position": 1}}, {"model": "game.charge", "pk": 2, "fields": {"zero_apartments": 50, "one_apartments": 250, "two_apartments": 750, "three_apartments": 1500, "four_apartments": 1750, "five_apartments": 2000}}, {"model": "game.card", "pk": 2, "fields": {"name": "B4", "cost": 500, "apartment_cost": 500, "hotel_cost": 2500, "deposit_value": 250, "charge": 2, "group_number": 0, "position": 2}}, {"model": "game.charge", "pk": 3, "fields": {"zero_apartments": 100, "one_apartments": 500, "two_apartments": 1500, "three_apartments": 3000, "four_apartments": 3500, "five_apartments": 4000}}, {"model": "game.card", "pk": 3, "fields": {"name": "E5", "cost": 1000, "apartment_cost": 750, "hotel_cost": 3750, "deposit_value": 500, "charge": 3, "group_number": 1, "position": 4}}, {"model": "game.charge", "pk": 4, "fields": {"zero_apartments": 100, "one_apartments": 500, "two_apartments": 1500, "three_apartments": 3000, "four_apartments": 3500, "five_apartments": 4000}}, {"model": "game.card", "pk": 4, "fields": {"name": "E1", "cost": 1000, "apartment_cost": 750, "hotel_cost": 3750, "deposit_value": 500, "charge": 4, "group_number": 1, "position": 5}}, {"model": "game.charge", "pk": 5, "fields": {"zero_apartments": 150, "one_apartments": 750, "two_apartments": 2250, "three_apartments": 4500, "four_apartments": 5250, "five_apartments": 6000}}, {"model": "game.card", "pk": 5, "fields": {"name": "C16", "cost": 1500, "apartment_cost": 1000, "hotel_cost": 5000, "deposit_value": 750, "charge": 5, "group_number": 2, "position": 7}}, {"model": "game.charge", "pk": 6, "fields": {"zero_apartments": 150, "one_apartments": 750, "two_apartments": 2250, "three_apartments": 4500, "four_apartments": 5250, "five_apartments": 6000}}, {"model": "game.card", "pk": 6, "fields": {"name": "C1", "cost": 1500, "apartment_cost": 1000, "hotel_cost": 5000, "deposit_value": 750, "charge": 6, "group_number": 2, "position": 8}}, {"model": "game.charge", "pk": 7, "fields": {"zero_apartments": 200, "one_apartments": 1000, "two_apartments": 3000, "three_apartments": 6000, "four_apartments": 7000, "five_apartments": 8000}}, {"model": "game.card", "pk": 7, "fields": {"name": "C5", "cost": 2000, "apartment_cost": 1250, "hotel_cost": 6250, "deposit_value": 1000, "charge": 7, "group_number": 3, "position": 10}}, {"model": "game.charge", "pk": 8, "fields": {"zero_apartments": 200, "one_apartments": 1000, "two_apartments": 3000, "three_apartments": 6000, "four_apartments": 7000, "five_apartments": 8000}}, {"model": "game.card", "pk": 8, "fields": {"name": "C7", "cost": 2000, "apartment_cost": 1250, "hotel_cost": 6250, "deposit_value": 1000, "charge": 8, "group_number": 3, "position": 11}}, {"model": "game.charge", "pk": 9, "fields": {"zero_apartments": 250, "one_apartments": 1250, "two_apartments": 3750, "three_apartments": 7500, "four_apartments": 8750, "five_apartments": 10000}}, {"model": "game.card", "pk": 9, "fields": {"name": "D1", "cost": 2500, "apartment_cost": 1500, "hotel_cost": 7500, "deposit_value": 1250, "charge": 9, "group_number": 4, "position": 13}}, {"model": "game.charge", "pk": 10, "fields": {"zero_apartments": 250, "one_apartments": 1250, "two_apartments": 3750, "three_apartments": 7500, "four_apartments": 8750, "five_apartments": 10000}}, {"model": "game.card", "pk": 10, "fields": {"name": "D2", "cost": 2500, "apartment_cost": 1500, "hotel_cost": 7500, "deposit_value": 1250, "charge": 10, "group_number": 4, "position": 14}}, {"model": "game.charge", "pk": 11, "fields": {"zero_apartments": 300, "one_apartments": 1500, "two_apartments": 4500, "three_apartments": 9000, "four_apartments": 10500, "five_apartments": 12000}}, {"model": "game.card", "pk": 11, "fields": {"name": "C4", "cost": 3000, "apartment_cost": 1750, "hotel_cost": 8750, "deposit_value": 1500, "charge": 11, "group_number": 5, "position": 16}}, {"model": "game.charge", "pk": 12, "fields": {"zero_apartments": 300, "one_apartments": 1500, "two_apartments": 4500, "three_apartments": 9000, "four_apartments": 10500, "five_apartments": 12000}}, {"model": "game.card", "pk": 12, "fields": {"name": "C3", "cost": 3000, "apartment_cost": 1750, "hotel_cost": 8750, "deposit_value": 1500, "charge": 12, "group_number": 5, "position": 17}}, {"model": "game.charge", "pk": 13, "fields": {"zero_apartments": 350, "one_apartments": 1750, "two_apartments": 5250, "three_apartments": 10500, "four_apartments": 12250, "five_apartments": 14000}}, {"model": "game.card", "pk": 13, "fields": {"name": "C8", "cost": 3500, "apartment_cost": 2000, "hotel_cost": 10000, "deposit_value": 1750, "charge": 13, "group_number": 6, "position": 19}}, {"model": "game.charge", "pk": 14, "fields": {"zero_apartments": 350, "one_apartments": 1750, "two_apartments": 5250, "three_apartments": 10500, "four_apartments": 12250, "five_apartments": 14000}}, {"model": "game.card", "pk": 14, "fields": {"name": "C13", "cost": 3500, "apartment_cost": 2000, "hotel_cost": 10000, "deposit_value": 1750, "charge": 14, "group_number": 6, "position": 20}}, {"model": "game.charge", "pk": 15, "fields": {"zero_apartments": 400, "one_apartments": 2000, "two_apartments": 6000, "three_apartments": 12000, "four_apartments": 14000, "five_apartments": 16000}}, {"model": "game.card", "pk": 15, "fields": {"name": "A2", "cost": 4000, "apartment_cost": 2250, "hotel_cost": 11250, "deposit_value": 2000, "charge": 15, "group_number": 7, "position": 22}}, {"model": "game.charge", "pk": 16, "fields": {"zero_apartments": 400, "one_apartments": 2000, "two_apartments": 6000, "three_apartments": 12000, "four_apartments": 14000, "five_apartments": 16000}}, {"model": "game.card", "pk": 16, "fields": {"name": "A1", "cost": 4000, "apartment_cost": 2250, "hotel_cost": 11250, "deposit_value": 2000, "charge": 16, "group_number": 7, "position": 23}}]